llm_smollm2/SmolLM2-135M-Instruct.Q4_1.gguf
llm_smollm2/__init__.py
llm_smollm2-0.1.1.dist-info/LICENSE
llm_smollm2-0.1.1.dist-info/METADATA
llm_smollm2-0.1.1.dist-info/WHEEL
llm_smollm2-0.1.1.dist-info/entry_points.txt
llm_smollm2-0.1.1.dist-info/top_level.txt
llm_smollm2-0.1.1.dist-info/RECORD
