Metadata-Version: 2.2
Name: llm-smollm2
Version: 0.1.1
Summary: SmolLM2-135M-Instruct.Q4_1 for LLM
Author: Simon Willison
License: Apache-2.0
Project-URL: Homepage, https://github.com/simonw/llm-smollm2
Project-URL: Changelog, https://github.com/simonw/llm-smollm2/releases
Project-URL: Issues, https://github.com/simonw/llm-smollm2/issues
Project-URL: CI, https://github.com/simonw/llm-smollm2/actions
Classifier: License :: OSI Approved :: Apache Software License
Requires-Python: >=3.9
License-File: LICENSE
Requires-Dist: llm
Requires-Dist: llama-cpp-python>=0.3.7
Provides-Extra: test
Requires-Dist: pytest; extra == "test"
